setup.py
onyx_sqlalchemy/__init__.py
onyx_sqlalchemy/_compat.py
onyx_sqlalchemy.egg-info/PKG-INFO
onyx_sqlalchemy.egg-info/SOURCES.txt
onyx_sqlalchemy.egg-info/dependency_links.txt
onyx_sqlalchemy.egg-info/not-zip-safe
onyx_sqlalchemy.egg-info/requires.txt
onyx_sqlalchemy.egg-info/top_level.txt